{
  "type": "Feature",
  "properties": {
    "iso:country":"KR",
    "name:eng_x_preferred":[
        "Dragon Hill Spa"
    ],
    "wof:name":"Dragon Hill Spa",
    "wof:placetype":"venue"
},
  "geometry": {"coordinates":[126.96369409560999,37.527510980167],"type":"Point"}
}