{
  "type": "Feature",
  "properties": {
    "iso:country":"KR",
    "name:eng_x_preferred":[
        "Ilmin Museum of Art"
    ],
    "wof:name":"Ilmin Museum of Art",
    "wof:placetype":"venue"
},
  "geometry": {"coordinates":[126.97751283645999,37.569888883467],"type":"Point"}
}