{
  "type": "Feature",
  "properties": {
    "iso:country":"KR",
    "name:eng_x_preferred":[
        "Dimensionplus Lab"
    ],
    "wof:name":"Dimensionplus Lab",
    "wof:placetype":"venue"
},
  "geometry": {"coordinates":[121.54006699999999,25.061042],"type":"Point"}
}