{
  "type": "Feature",
  "properties": {
    "iso:country":"KR",
    "name:eng_x_preferred":[
        "Johngmyo Shrine"
    ],
    "wof:name":"Johngmyo Shrine",
    "wof:placetype":"venue"
},
  "geometry": {"coordinates":[126.99382066727,37.574667857178],"type":"Point"}
}